mdtoword/__init__.py
mdtoword/converter.py
tests/__init__.py
tests/test_converter.py
mdtoword-0.1.0.dist-info/LICENSE
mdtoword-0.1.0.dist-info/METADATA
mdtoword-0.1.0.dist-info/WHEEL
mdtoword-0.1.0.dist-info/top_level.txt
mdtoword-0.1.0.dist-info/RECORD
