Metadata-Version: 2.1
Name: mdtoword
Version: 0.1.0
Summary: A Python package to convert Markdown files to Word documents with advanced formatting
Home-page: https://github.com/gioahumada/mdtoword
Author: Gio Ahumada
Author-email: giovanni.ahumada.t@gmail.com
Classifier: Programming Language :: Python :: 3
Classifier: License :: OSI Approved :: MIT License
Classifier: Operating System :: OS Independent
Requires-Python: >=3.6
License-File: LICENSE
Requires-Dist: python-docx
Requires-Dist: markdown
Requires-Dist: beautifulsoup4
